litemigrate/__init__.py
litemigrate/migrate.py
litemigrate-0.0.3.dist-info/METADATA
litemigrate-0.0.3.dist-info/WHEEL
litemigrate-0.0.3.dist-info/entry_points.txt
litemigrate-0.0.3.dist-info/licenses/LICENSE
litemigrate-0.0.3.dist-info/RECORD
