Metadata-Version: 2.1
Name: litemigrate
Version: 0.0.3
Summary: Extremely simple SQLite migrations
Project-URL: Homepage, https://github.com/imryche/litemigrate
Project-URL: Issues, https://github.com/imryche/litemigrate/issues
Author-email: Dima Charnyshou <imryche13@gmail.com>
License-File: LICENSE
Classifier: License :: OSI Approved :: MIT License
Classifier: Operating System :: OS Independent
Classifier: Programming Language :: Python :: 3
Requires-Python: >=3.8
